{
  "project_info": {
    "project_number": "786705171341",
    "project_id": "myapp1-cf259",
    "storage_bucket": "myapp1-cf259.appspot.com"
  },
  "client": [
    {
      "client_info": {
        "mobilesdk_app_id": "1:786705171341:android:b0ac5f483a8b99c8ff73c4",
        "android_client_info": {
          "package_name": "com.example.flutter_application_1_test"
        }
      },
      "oauth_client": [
        {
          "client_id": "786705171341-ckg41r1evlkl72sv59vg9ndp07r5re8b.apps.googleusercontent.com",
          "client_type": 3
        }
      ],
      "api_key": [
        {
          "current_key": "AIzaSyACEXFOBV2ilHzYXpra08tl47XcrxNn700"
        }
      ],
      "services": {
        "appinvite_service": {
          "other_platform_oauth_client": [
            {
              "client_id": "786705171341-ckg41r1evlkl72sv59vg9ndp07r5re8b.apps.googleusercontent.com",
              "client_type": 3
            }
          ]
        }
      }
    }
  ],
  "configuration_version": "1"
}